MoneyMate/__init__.py
MoneyMate/__main__.py
MoneyMate/data_layer/__init__.py
MoneyMate/data_layer/api.py
MoneyMate/data_layer/auth.py
MoneyMate/data_layer/categories.py
MoneyMate/data_layer/contacts.py
MoneyMate/data_layer/database.py
MoneyMate/data_layer/expenses.py
MoneyMate/data_layer/logging_config.py
MoneyMate/data_layer/manager.py
MoneyMate/data_layer/schema_utils.py
MoneyMate/data_layer/transactions.py
MoneyMate/data_layer/usermanager.py
MoneyMate/data_layer/validation.py
MoneyMate/gui/__init__.py
MoneyMate/gui/app.py
MoneyMate/gui/categories_frame.py
MoneyMate/gui/charts_frame.py
MoneyMate/gui/contacts_frame.py
MoneyMate/gui/expenses_frame.py
MoneyMate/gui/login_frame.py
MoneyMate/gui/register_frame.py
MoneyMate/gui/transactions_frame.py
moneymate-1.1.4.dist-info/licenses/LICENSE
moneymate-1.1.4.dist-info/METADATA
moneymate-1.1.4.dist-info/WHEEL
moneymate-1.1.4.dist-info/top_level.txt
moneymate-1.1.4.dist-info/RECORD
