Metadata-Version: 2.4
Name: MoneyMate
Version: 1.1.4
Summary: Description of the project here
Home-page: https://github.com/aequitas-aod/MoneyMate
Author: Name Surname
Author-email: name.surname@organization.domain
License: Apache 2.0 License
Project-URL: Bug Reports, https://github.com/aequitas-aod/MoneyMate/issues
Project-URL: Source, https://github.com/aequitas-aod/MoneyMate
Keywords: aeuitas,horizon2020,xai,bias
Platform: Independant
Classifier: Development Status :: 3 - Alpha
Classifier: Intended Audience :: Developers
Classifier: Topic :: Software Development :: Libraries
Classifier: Topic :: Scientific/Engineering :: Artificial Intelligence
Classifier: License :: OSI Approved :: Apache Software License
Classifier: Programming Language :: Python :: 3
Classifier: Programming Language :: Python :: 3 :: Only
Requires-Python: >=3.11.9
License-File: LICENSE
Requires-Dist: scikit-learn>=1.4.1.post1
Requires-Dist: pandas>=2.2.1
Requires-Dist: matplotlib<3.10; python_version < "3.10"
Requires-Dist: matplotlib>=3.10; python_version >= "3.10"
Requires-Dist: Werkzeug>=3.0.0
Requires-Dist: passlib>=1.7.4
Requires-Dist: bcrypt>=4.1.2
Requires-Dist: PyJWT>=2.8.0
Dynamic: author
Dynamic: author-email
Dynamic: classifier
Dynamic: description
Dynamic: description-content-type
Dynamic: home-page
Dynamic: keywords
Dynamic: license
Dynamic: license-file
Dynamic: platform
Dynamic: project-url
Dynamic: requires-dist
Dynamic: requires-python
Dynamic: summary
